envie/__init__.py
envie/activate_closest.py
envie/filters.py
envie/utils.py
envie-0.4.36.data/scripts/envie
envie-0.4.36.data/scripts/envie-tmp
envie-0.4.36.data/scripts/envie-tools
envie-0.4.36.dist-info/DESCRIPTION.rst
envie-0.4.36.dist-info/METADATA
envie-0.4.36.dist-info/RECORD
envie-0.4.36.dist-info/WHEEL
envie-0.4.36.dist-info/metadata.json
envie-0.4.36.dist-info/top_level.txt
