Metadata-Version: 2.0
Name: envie
Version: 0.4.36
Summary: Bash helpers for navigating and managing Python VirtualEnvs.
Home-page: https://github.com/randomir/envie
Author: Radomir Stevanovic
Author-email: radomir.stevanovic@gmail.com
License: MIT
Keywords: virtualenv bash helper closest virtual environment create mkenv destroy rmenv change chenv activate discover find findenv list lsenv cdenv
Platform: UNKNOWN
Classifier: Development Status :: 4 - Beta
Classifier: Intended Audience :: Developers
Classifier: Programming Language :: Python
Classifier: Programming Language :: Python :: 2
Classifier: Programming Language :: Python :: 2.6
Classifier: Programming Language :: Python :: 2.7
Classifier: Programming Language :: Python :: 3
Classifier: Programming Language :: Python :: 3.3
Classifier: Programming Language :: Python :: 3.4
Classifier: Programming Language :: Python :: 3.5
Classifier: Programming Language :: Python :: 3.6
Classifier: Programming Language :: Unix Shell
Classifier: License :: OSI Approved :: MIT License
Classifier: Operating System :: POSIX
Classifier: Topic :: Utilities
Classifier: Topic :: System :: Shells
